lan_host_communication/__init__.py
lan_host_communication/client.py
lan_host_communication/server.py
lan_communication-1.0.dist-info/LICENSE
lan_communication-1.0.dist-info/METADATA
lan_communication-1.0.dist-info/WHEEL
lan_communication-1.0.dist-info/top_level.txt
lan_communication-1.0.dist-info/RECORD
